Workbook

Sheet Master Data
A1: schema_version | B1: payslip_id | C1: molga_country_grouping | D1: employer_name | E1: employer_tax_id_1_type | F1: employer_tax_id_1 | G1: employer_tax_id_1_country | H1: employer_tax_id_2_type | I1: employer_tax_id_2 | J1: employer_tax_id_2_country | K1: employer_address_line1 | L1: employer_address_line2 | M1: employer_city | N1: employer_state | O1: employer_postal_code | P1: employer_country_code | Q1: employer_branch_name | R1: employer_branch_country_code | S1: employee_first_name | T1: employee_middle_name | U1: employee_last_name | V1: employee_address_line1 | W1: employee_city | X1: employee_state | Y1: employee_postal_code | Z1: employee_country_code | AA1: employee_id | AB1: personnel_number | AC1: payroll_id | AD1: tax_code | AE1: job_title | AF1: department | AG1: basic_rate_code | AH1: basic_salary | AI1: employment_group | AJ1: personnel_area | AK1: marital_status | AL1: payment_method | AM1: bank_account_number | AN1: salary_account | AO1: payroll_country_code | AP1: payroll_currency | AQ1: payment_currency | AR1: pay_frequency | AS1: pay_period_start | AT1: pay_period_end | AU1: payment_date | AV1: tax_year | AW1: cost_center | AX1: payroll_reference
A2: 1.1.0 | B2: us-90088-2025-02-22-000000900004502 | C2: 10 | D2: Brightmoor Composites, Inc | E2: EMPLOYER_ID | F2: 075701781 | G2: US | H2: OREGON_EMPLOYER_BIN | I2: 0014187 | J2: US | K2: 4100 Larkspur Commons Dr | L2: Suite 210 | M2: Wilsonville | N2: OR | O2: 97070 | P2: US | Q2: BMCWV | R2: US | S2: Lena | T2: Marie | U2: Vostrikova | V2: 1820 SE Wrenfield Ct | W2: Portland | X2: OR | Y2: 97214 | Z2: US | AA2: 90088 | AB2: 90088 | AC2: 000000900004502 | AD2: Federal=Single; State=Single; Federal Allowances=0; State Allowances=1 | AE2: Data Analyst | AF2: 1104100-DATA & INSIGHTS | AG2: BIWEEKLY | AH2: 3384.62 | AI2: BW1-Biweekly Salaried Exempt | AJ2: Composites Division | AK2: Single | AL2: DIRECT_DEPOSIT | AM2: 9999324423 | AN2: 9999324423 | AO2: US | AP2: USD | AQ2: USD | AR2: BIWEEKLY | AS2: 2025-02-22 | AT2: 2025-03-07 | AU2: 2025-03-07 | AV2: 2025 | AW2: 1104100-DATA & INSIGHTS | AX2: BMCWV/000000900004502
A3: 1.1.0 | B3: us-90177-2025-01-25-000000900009523 | C3: 10 | D3: Quillon Medical Systems LLC | E3: EMPLOYER_ID | F3: 086628435 | G3: US | H3: OREGON_EMPLOYER_BIN | I3: 0077050 | J3: US | K3: 77 Tidewater Crossing | L3: P. O. Box 5120 | M3: Wilmington | N3: DE | O3: 19801 | P3: US | Q3: QMSWL | R3: US | S3: Jonah | T3: Everett | U3: Pelletier | V3: 3047 NW Thornbury Ln | W3: Corvallis | X3: OR | Y3: 97330 | Z3: US | AA3: 90177 | AB3: 90177 | AC3: 000000900009523 | AD3: Federal=Married; State=Married; Federal Allowances=0; State Allowances=2 | AE3: Process Engineer | AF3: 2206200-PROCESS ENGINEERING | AG3: BIWEEKLY | AH3: 3826.92 | AI3: BW1-Biweekly Salaried Exempt | AJ3: Diagnostics Unit | AK3: Married | AL3: DIRECT_DEPOSIT | AM3: 9999957806 | AN3: 9999957806 | AO3: US | AP3: USD | AQ3: USD | AR3: BIWEEKLY | AS3: 2025-01-25 | AT3: 2025-02-07 | AU3: 2025-02-07 | AV3: 2025 | AW3: 2206200-PROCESS ENGINEERING | AX3: QMSWL/000000900009523
A4: 1.1.0 | B4: us-90283-2025-04-05-000000900019134 | C4: 10 | D4: Orrin Vale Engineering Corp | E4: EMPLOYER_ID | F4: 099850569 | G4: US | H4: OREGON_EMPLOYER_BIN | I4: 0022800 | J4: US | K4: 9200 Fennimore Tech Loop | L4: Building B | M4: Austin | N4: TX | O4: 78758 | P4: US | Q4: OVEAU | R4: US | S4: Meera | T4: Kavya | U4: Sundaresan | V4: 645 SW Ashcombe Dr | W4: Beaverton | X4: OR | Y4: 97005 | Z4: US | AA4: 90283 | AB4: 90283 | AC4: 000000900019134 | AD4: Federal=Single; State=Single; Federal Allowances=0; State Allowances=0 | AE4: Senior Software Engineer | AF4: 3308300-PLATFORM SERVICES | AG4: BIWEEKLY | AH4: 5615.38 | AI4: BW1-Biweekly Salaried Exempt | AJ4: Engineering Services | AK4: Single | AL4: DIRECT_DEPOSIT | AM4: 9999160538 | AN4: 9999160538 | AO4: US | AP4: USD | AQ4: USD | AR4: BIWEEKLY | AS4: 2025-04-05 | AT4: 2025-04-18 | AU4: 2025-04-18 | AV4: 2025 | AW4: 3308300-PLATFORM SERVICES | AX4: OVEAU/000000900019134
A5: 1.1.0 | B5: us-90372-2025-04-05-000000900028576 | C5: 10 | D5: Hollowfield Provisions Co | E5: EMPLOYER_ID | F5: 175838079 | G5: US | H5: OREGON_EMPLOYER_BIN | I5: 0053989 | J5: US | K5: 512 Marrowstone Way | M5: Boise | N5: ID | O5: 83702 | P5: US | Q5: HFPBO | R5: US | S5: Tobias | T5: Adewale | U5: Nwachukwu | V5: 1190 Larchmere St NE | W5: Salem | X5: OR | Y5: 97301 | Z5: US | AA5: 90372 | AB5: 90372 | AC5: 000000900028576 | AD5: Federal=Married; State=Married; Federal Allowances=0; State Allowances=3 | AE5: Quality Technician | AF5: 4402400-QUALITY CONTROL | AG5: BIWEEKLY | AH5: 2788.46 | AI5: BW1-Biweekly Salaried Exempt | AJ5: Food Operations | AK5: Married | AL5: DIRECT_DEPOSIT | AM5: 9999281334 | AN5: 9999281334 | AO5: US | AP5: USD | AQ5: USD | AR5: BIWEEKLY | AS5: 2025-04-05 | AT5: 2025-04-18 | AU5: 2025-04-18 | AV5: 2025 | AW5: 4402400-QUALITY CONTROL | AX5: HFPBO/000000900028576
A6: 1.1.0 | B6: us-90417-2025-06-14-000000900038344 | C6: 10 | D6: Tarnwick Software, Inc | E6: EMPLOYER_ID | F6: 182687783 | G6: US | H6: OREGON_EMPLOYER_BIN | I6: 0041580 | J6: US | K6: 1880 Cindermoss Ave | L6: Floor 7 | M6: Seattle | N6: WA | O6: 98109 | P6: US | Q6: TSWSE | R6: US | S6: Clara | T6: Beatriz | U6: Montalvo | V6: 2786 Selwyn Hollow Rd | W6: Eugene | X6: OR | Y6: 97405 | Z6: US | AA6: 90417 | AB6: 90417 | AC6: 000000900038344 | AD6: Federal=Single; State=Single; Federal Allowances=0; State Allowances=1 | AE6: Product Owner | AF6: 5510500-DIGITAL PRODUCTS | AG6: BIWEEKLY | AH6: 4884.62 | AI6: BW1-Biweekly Salaried Exempt | AJ6: Cloud Products | AK6: Single | AL6: DIRECT_DEPOSIT | AM6: 9999275344 | AN6: 9999275344 | AO6: US | AP6: USD | AQ6: USD | AR6: BIWEEKLY | AS6: 2025-06-14 | AT6: 2025-06-27 | AU6: 2025-06-27 | AV6: 2025 | AW6: 5510500-DIGITAL PRODUCTS | AX6: TSWSE/000000900038344
A7: 1.1.0 | B7: us-90487-2025-01-25-000000900046035 | C7: 10 | D7: Elderquay Forest Products LLC | E7: EMPLOYER_ID | F7: 196840230 | G7: US | H7: OREGON_EMPLOYER_BIN | I7: 0076430 | J7: US | K7: 3305 Bramblewick Rd | M7: Eugene | N7: OR | O7: 97402 | P7: US | Q7: EQFEU | R7: US | S7: Declan | T7: Hugh | U7: Ferriday | V7: 834 E Galloway Ridge | W7: Hillsboro | X7: OR | Y7: 97123 | Z7: US | AA7: 90487 | AB7: 90487 | AC7: 000000900046035 | AD7: Federal=Married; State=Married; Federal Allowances=0; State Allowances=2 | AE7: Research Chemist | AF7: 6603600-MATERIALS RESEARCH | AG7: BIWEEKLY | AH7: 4153.85 | AI7: BW1-Biweekly Salaried Exempt | AJ7: Engineered Materials | AK7: Married | AL7: DIRECT_DEPOSIT | AM7: 9999719750 | AN7: 9999719750 | AO7: US | AP7: USD | AQ7: USD | AR7: BIWEEKLY | AS7: 2025-01-25 | AT7: 2025-02-07 | AU7: 2025-02-07 | AV7: 2025 | AW7: 6603600-MATERIALS RESEARCH | AX7: EQFEU/000000900046035
A8: 1.1.0 | B8: us-90614-2025-07-12-000000900047520 | C8: 10 | D8: Varnell Insight Partners, Inc | E8: EMPLOYER_ID | F8: 289016935 | G8: US | H8: OREGON_EMPLOYER_BIN | I8: 0084357 | J8: US | K8: 240 Oxley Wharf St | L8: Suite 1400 | M8: Philadelphia | N8: PA | O8: 19103 | P8: US | Q8: VIPPH | R8: US | S8: Yasmin | T8: Leila | U8: Haddad-Ortiz | V8: 219 N Pembrook Trl | W8: Ashland | X8: OR | Y8: 97520 | Z8: US | AA8: 90614 | AB8: 90614 | AC8: 000000900047520 | AD8: Federal=Single; State=Single; Federal Allowances=0; State Allowances=0 | AE8: People Partner | AF8: 7701700-PEOPLE OPERATIONS | AG8: BIWEEKLY | AH8: 3326.92 | AI8: BW1-Biweekly Salaried Exempt | AJ8: Corporate Services | AK8: Single | AL8: DIRECT_DEPOSIT | AM8: 9999542561 | AN8: 9999542561 | AO8: US | AP8: USD | AQ8: USD | AR8: BIWEEKLY | AS8: 2025-07-12 | AT8: 2025-07-25 | AU8: 2025-07-25 | AV8: 2025 | AW8: 7701700-PEOPLE OPERATIONS | AX8: VIPPH/000000900047520
A9: 1.1.0 | B9: us-90721-2025-02-08-000000900056819 | C9: 10 | D9: Stellhaven Aero Components Corp | E9: EMPLOYER_ID | F9: 293160496 | G9: US | H9: OREGON_EMPLOYER_BIN | I9: 0021846 | J9: US | K9: 6610 Kestrelmoor Blvd | L9: Hangar 4 | M9: Hillsboro | N9: OR | O9: 97124 | P9: US | Q9: SACHI | R9: US | S9: Callum | T9: Reid | U9: Strathmore | V9: 1402 NE Quenby Pl | W9: Bend | X9: OR | Y9: 97701 | Z9: US | AA9: 90721 | AB9: 90721 | AC9: 000000900056819 | AD9: Federal=Married; State=Married; Federal Allowances=0; State Allowances=1 | AE9: Production Lead | AF9: 8805800-PRODUCTION | AG9: BIWEEKLY | AH9: 3500 | AI9: BW1-Biweekly Salaried Exempt | AJ9: Aero Structures | AK9: Married | AL9: DIRECT_DEPOSIT | AM9: 9999952704 | AN9: 9999952704 | AO9: US | AP9: USD | AQ9: USD | AR9: BIWEEKLY | AS9: 2025-02-08 | AT9: 2025-02-21 | AU9: 2025-02-21 | AV9: 2025 | AW9: 8805800-PRODUCTION | AX9: SACHI/000000900056819
A10: 1.1.0 | B10: us-90848-2025-02-22-000000900066265 | C10: 10 | D10: Marrowgate Clinical LLC | E10: EMPLOYER_ID | F10: 497203187 | G10: US | H10: OREGON_EMPLOYER_BIN | I10: 0098756 | J10: US | K10: 915 Plover Hollow St | L10: Suite 600 | M10: San Francisco | N10: CA | O10: 94105 | P10: US | Q10: MGCSF | R10: US | S10: Ines | T10: Carolina | U10: Rebelo | V10: 3318 Whitlock Crest SE | W10: Salem | X10: OR | Y10: 97302 | Z10: US | AA10: 90848 | AB10: 90848 | AC10: 000000900066265 | AD10: Federal=Single; State=Single; Federal Allowances=0; State Allowances=1 | AE10: Clinical Trial Coordinator | AF10: 9902900-CLINICAL OPERATIONS | AG10: BIWEEKLY | AH10: 3134.62 | AI10: BW1-Biweekly Salaried Exempt | AJ10: Clinical Studies | AK10: Single | AL10: DIRECT_DEPOSIT | AM10: 9999804441 | AN10: 9999804441 | AO10: US | AP10: USD | AQ10: USD | AR10: BIWEEKLY | AS10: 2025-02-22 | AT10: 2025-03-07 | AU10: 2025-03-07 | AV10: 2025 | AW10: 9902900-CLINICAL OPERATIONS | AX10: MGCSF/000000900066265
A11: 1.1.0 | B11: us-90942-2025-03-08-000000900072973 | C11: 10 | D11: Duncairn Fabrication Co | E11: EMPLOYER_ID | F11: 699997446 | G11: US | H11: OREGON_EMPLOYER_BIN | I11: 0012112 | J11: US | K11: 2475 Ironthistle Ave | M11: Salt Lake City | N11: UT | O11: 84104 | P11: US | Q11: DFCSL | R11: US | S11: Haruto | T11: Ken | U11: Aoyagi | V11: 1566 SW Dorrance Ave | W11: Portland | X11: OR | Y11: 97201 | Z11: US | AA11: 90942 | AB11: 90942 | AC11: 000000900072973 | AD11: Federal=Married; State=Married; Federal Allowances=0; State Allowances=2 | AE11: Simulation Analyst | AF11: 1207100-DIGITAL ENGINEERING | AG11: BIWEEKLY | AH11: 4730.77 | AI11: BW1-Biweekly Salaried Exempt | AJ11: Heavy Fabrication | AK11: Married | AL11: DIRECT_DEPOSIT | AM11: 9999391819 | AN11: 9999391819 | AO11: US | AP11: USD | AQ11: USD | AR11: BIWEEKLY | AS11: 2025-03-08 | AT11: 2025-03-21 | AU11: 2025-03-21 | AV11: 2025 | AW11: 1207100-DIGITAL ENGINEERING | AX11: DFCSL/000000900072973

Sheet Pay Line Items
A1: payslip_id | B1: employee_id | C1: section | D1: applies_to | E1: wage_code | F1: wage_type | G1: unit | H1: quantity | I1: base | J1: employee_rate | K1: employee_amount | L1: employer_amount | M1: amount | N1: share | O1: tax_treatment | P1: kind | Q1: line_category
A2: us-90088-2025-02-22-000000900004502 | B2: 90088 | C2: EARNING | D2: CURRENT | E2: 1000 | F2: Regular Salary | G2: HOURS | H2: 64 | J2: 42.31 | K2: 2707.66 | M2: 2707.66 | N2: EMPLOYEE | O2: TAXABLE | P2: OTHER | Q2: EARNING
A3: us-90088-2025-02-22-000000900004502 | B3: 90088 | C3: EARNING | D3: CURRENT | E3: 1110 | F3: Vacation Pay | G3: HOURS | H3: 16 | J3: 42.31 | K3: 676.96 | M3: 676.96 | N3: EMPLOYEE | O3: TAXABLE | P3: LEAVE | Q3: EARNING
A4: us-90088-2025-02-22-000000900004502 | B4: 90088 | C4: EARNING | D4: CURRENT | E4: 1510 | F4: Group Term Life Imputed | K4: 7.5 | M4: 7.5 | N4: EMPLOYEE | O4: TAXABLE | P4: OTHER | Q4: IMPUTED_INCOME
A5: us-90088-2025-02-22-000000900004502 | B5: 90088 | C5: DEDUCTION | D5: CURRENT | E5: 4010 | F5: Federal Income Tax | I5: 3034.5 | K5: 345.05 | M5: 345.05 | N5: EMPLOYEE | O5: TAXABLE | P5: OTHER | Q5: US_TAX
A6: us-90088-2025-02-22-000000900004502 | B6: 90088 | C6: DEDUCTION | D6: CURRENT | E6: 4050 | F6: Medicare EE | I6: 3305.27 | K6: 47.93 | M6: 47.93 | N6: EMPLOYEE | O6: TAXABLE | P6: HEALTH | Q6: US_TAX
A7: us-90088-2025-02-22-000000900004502 | B7: 90088 | C7: DEDUCTION | D7: CURRENT | E7: 4030 | F7: Social Security EE | I7: 3305.27 | K7: 204.93 | M7: 204.93 | N7: EMPLOYEE | O7: TAXABLE | P7: OTHER | Q7: US_TAX
A8: us-90088-2025-02-22-000000900004502 | B8: 90088 | C8: DEDUCTION | D8: CURRENT | E8: 4120 | F8: OR Paid Leave EE | I8: 3392.12 | K8: 20.35 | M8: 20.35 | N8: EMPLOYEE | O8: TAXABLE | P8: HEALTH | Q8: US_TAX
A9: us-90088-2025-02-22-000000900004502 | B9: 90088 | C9: DEDUCTION | D9: CURRENT | E9: 4110 | F9: OR State Income Tax | I9: 3034.5 | K9: 224.4 | M9: 224.4 | N9: EMPLOYEE | O9: TAXABLE | P9: OTHER | Q9: US_TAX
A10: us-90088-2025-02-22-000000900004502 | B10: 90088 | C10: DEDUCTION | D10: CURRENT | E10: 4130 | F10: OR Statewide Transit Tax | I10: 3392.12 | K10: 3.39 | M10: 3.39 | N10: EMPLOYEE | O10: TAXABLE | P10: OTHER | Q10: US_TAX
A11: us-90088-2025-02-22-000000900004502 | B11: 90088 | C11: DEDUCTION | D11: CURRENT | E11: 5000 | F11: 401(k) Pre-Tax | K11: 270.77 | M11: 270.77 | N11: EMPLOYEE | O11: EXEMPT | P11: RETIREMENT | Q11: PRE_TAX_DEDUCTION
A12: us-90088-2025-02-22-000000900004502 | B12: 90088 | C12: DEDUCTION | D12: CURRENT | E12: 5120 | F12: Vision Pre-Tax | K12: 4.6 | M12: 4.6 | N12: EMPLOYEE | O12: EXEMPT | P12: HEALTH | Q12: PRE_TAX_DEDUCTION
A13: us-90088-2025-02-22-000000900004502 | B13: 90088 | C13: DEDUCTION | D13: CURRENT | E13: 5110 | F13: Dental Pre-Tax | K13: 10.85 | M13: 10.85 | N13: EMPLOYEE | O13: EXEMPT | P13: HEALTH | Q13: PRE_TAX_DEDUCTION
A14: us-90088-2025-02-22-000000900004502 | B14: 90088 | C14: DEDUCTION | D14: CURRENT | E14: 5100 | F14: Medical Pre-Tax | K14: 71.4 | M14: 71.4 | N14: EMPLOYEE | O14: EXEMPT | P14: HEALTH | Q14: PRE_TAX_DEDUCTION
A15: us-90088-2025-02-22-000000900004502 | B15: 90088 | C15: ER_CONTRIB | D15: CURRENT | E15: 7000 | F15: 401(k) Employer Match | L15: 101.54 | M15: 101.54 | N15: EMPLOYER | O15: EXEMPT | P15: RETIREMENT | Q15: EMPLOYER_PAID_BENEFIT
A16: us-90088-2025-02-22-000000900004502 | B16: 90088 | C16: ER_CONTRIB | D16: CURRENT | E16: 7100 | F16: Medical Employer Contribution | L16: 527.65 | M16: 527.65 | N16: EMPLOYER | O16: EXEMPT | P16: HEALTH | Q16: EMPLOYER_PAID_BENEFIT
A17: us-90177-2025-01-25-000000900009523 | B17: 90177 | C17: EARNING | D17: CURRENT | E17: 1000 | F17: Regular Salary | G17: HOURS | H17: 72 | J17: 47.84 | K17: 3444.2 | M17: 3444.2 | N17: EMPLOYEE | O17: TAXABLE | P17: OTHER | Q17: EARNING
A18: us-90177-2025-01-25-000000900009523 | B18: 90177 | C18: EARNING | D18: CURRENT | E18: 1100 | F18: Holiday Pay | G18: HOURS | H18: 8 | J18: 47.84 | K18: 382.72 | M18: 382.72 | N18: EMPLOYEE | O18: TAXABLE | P18: LEAVE | Q18: EARNING
A19: us-90177-2025-01-25-000000900009523 | B19: 90177 | C19: EARNING | D19: CURRENT | E19: 1510 | F19: Group Term Life Imputed | K19: 5.24 | M19: 5.24 | N19: EMPLOYEE | O19: TAXABLE | P19: OTHER | Q19: IMPUTED_INCOME
A20: us-90177-2025-01-25-000000900009523 | B20: 90177 | C20: DEDUCTION | D20: CURRENT | E20: 4010 | F20: Federal Income Tax | I20: 3418.89 | K20: 253.46 | M20: 253.46 | N20: EMPLOYEE | O20: TAXABLE | P20: OTHER | Q20: US_TAX
A21: us-90177-2025-01-25-000000900009523 | B21: 90177 | C21: DEDUCTION | D21: CURRENT | E21: 4050 | F21: Medicare EE | I21: 3648.51 | K21: 52.9 | M21: 52.9 | N21: EMPLOYEE | O21: TAXABLE | P21: HEALTH | Q21: US_TAX
A22: us-90177-2025-01-25-000000900009523 | B22: 90177 | C22: DEDUCTION | D22: CURRENT | E22: 4030 | F22: Social Security EE | I22: 3648.51 | K22: 226.21 | M22: 226.21 | N22: EMPLOYEE | O22: TAXABLE | P22: OTHER | Q22: US_TAX
A23: us-90177-2025-01-25-000000900009523 | B23: 90177 | C23: DEDUCTION | D23: CURRENT | E23: 4120 | F23: OR Paid Leave EE | I23: 3832.16 | K23: 22.99 | M23: 22.99 | N23: EMPLOYEE | O23: TAXABLE | P23: HEALTH | Q23: US_TAX
A24: us-90177-2025-01-25-000000900009523 | B24: 90177 | C24: DEDUCTION | D24: CURRENT | E24: 4110 | F24: OR State Income Tax | I24: 3418.89 | K24: 226.76 | M24: 226.76 | N24: EMPLOYEE | O24: TAXABLE | P24: OTHER | Q24: US_TAX
A25: us-90177-2025-01-25-000000900009523 | B25: 90177 | C25: DEDUCTION | D25: CURRENT | E25: 4130 | F25: OR Statewide Transit Tax | I25: 3832.16 | K25: 3.83 | M25: 3.83 | N25: EMPLOYEE | O25: TAXABLE | P25: OTHER | Q25: US_TAX
A26: us-90177-2025-01-25-000000900009523 | B26: 90177 | C26: DEDUCTION | D26: CURRENT | E26: 5000 | F26: 401(k) Pre-Tax | K26: 229.62 | M26: 229.62 | N26: EMPLOYEE | O26: EXEMPT | P26: RETIREMENT | Q26: PRE_TAX_DEDUCTION
A27: us-90177-2025-01-25-000000900009523 | B27: 90177 | C27: DEDUCTION | D27: CURRENT | E27: 5120 | F27: Vision Pre-Tax | K27: 9.35 | M27: 9.35 | N27: EMPLOYEE | O27: EXEMPT | P27: HEALTH | Q27: PRE_TAX_DEDUCTION
A28: us-90177-2025-01-25-000000900009523 | B28: 90177 | C28: DEDUCTION | D28: CURRENT | E28: 5110 | F28: Dental Pre-Tax | K28: 23.1 | M28: 23.1 | N28: EMPLOYEE | O28: EXEMPT | P28: HEALTH | Q28: PRE_TAX_DEDUCTION
A29: us-90177-2025-01-25-000000900009523 | B29: 90177 | C29: DEDUCTION | D29: CURRENT | E29: 5100 | F29: Medical Pre-Tax | K29: 151.2 | M29: 151.2 | N29: EMPLOYEE | O29: EXEMPT | P29: HEALTH | Q29: PRE_TAX_DEDUCTION
A30: us-90177-2025-01-25-000000900009523 | B30: 90177 | C30: ER_CONTRIB | D30: CURRENT | E30: 7000 | F30: 401(k) Employer Match | L30: 114.81 | M30: 114.81 | N30: EMPLOYER | O30: EXEMPT | P30: RETIREMENT | Q30: EMPLOYER_PAID_BENEFIT
A31: us-90177-2025-01-25-000000900009523 | B31: 90177 | C31: ER_CONTRIB | D31: CURRENT | E31: 7100 | F31: Medical Employer Contribution | L31: 798.34 | M31: 798.34 | N31: EMPLOYER | O31: EXEMPT | P31: HEALTH | Q31: EMPLOYER_PAID_BENEFIT
A32: us-90283-2025-04-05-000000900019134 | B32: 90283 | C32: EARNING | D32: CURRENT | E32: 1000 | F32: Regular Salary | G32: HOURS | H32: 48 | J32: 70.19 | K32: 3369.3 | M32: 3369.3 | N32: EMPLOYEE | O32: TAXABLE | P32: OTHER | Q32: EARNING
A33: us-90283-2025-04-05-000000900019134 | B33: 90283 | C33: EARNING | D33: CURRENT | E33: 1100 | F33: Holiday Pay | G33: HOURS | H33: 8 | J33: 70.19 | K33: 561.52 | M33: 561.52 | N33: EMPLOYEE | O33: TAXABLE | P33: LEAVE | Q33: EARNING
A34: us-90283-2025-04-05-000000900019134 | B34: 90283 | C34: EARNING | D34: CURRENT | E34: 1110 | F34: Vacation Pay | G34: HOURS | H34: 24 | J34: 70.19 | K34: 1684.56 | M34: 1684.56 | N34: EMPLOYEE | O34: TAXABLE | P34: LEAVE | Q34: EARNING
A35: us-90283-2025-04-05-000000900019134 | B35: 90283 | C35: EARNING | D35: CURRENT | E35: 1500 | F35: Domestic Partner Imputed Income | K35: 309.06 | M35: 309.06 | N35: EMPLOYEE | O35: TAXABLE | P35: OTHER | Q35: IMPUTED_INCOME
A36: us-90283-2025-04-05-000000900019134 | B36: 90283 | C36: EARNING | D36: CURRENT | E36: 1510 | F36: Group Term Life Imputed | K36: 5.87 | M36: 5.87 | N36: EMPLOYEE | O36: TAXABLE | P36: OTHER | Q36: IMPUTED_INCOME
A37: us-90283-2025-04-05-000000900019134 | B37: 90283 | C37: DEDUCTION | D37: CURRENT | E37: 4010 | F37: Federal Income Tax | I37: 5010.65 | K37: 788.98 | M37: 788.98 | N37: EMPLOYEE | O37: TAXABLE | P37: OTHER | Q37: US_TAX
A38: us-90283-2025-04-05-000000900019134 | B38: 90283 | C38: DEDUCTION | D38: CURRENT | E38: 4050 | F38: Medicare EE | I38: 5852.96 | K38: 84.87 | M38: 84.87 | N38: EMPLOYEE | O38: TAXABLE | P38: HEALTH | Q38: US_TAX
A39: us-90283-2025-04-05-000000900019134 | B39: 90283 | C39: DEDUCTION | D39: CURRENT | E39: 4030 | F39: Social Security EE | I39: 5852.96 | K39: 362.88 | M39: 362.88 | N39: EMPLOYEE | O39: TAXABLE | P39: OTHER | Q39: US_TAX
A40: us-90283-2025-04-05-000000900019134 | B40: 90283 | C40: DEDUCTION | D40: CURRENT | E40: 4120 | F40: OR Paid Leave EE | I40: 5930.31 | K40: 35.58 | M40: 35.58 | N40: EMPLOYEE | O40: TAXABLE | P40: HEALTH | Q40: US_TAX
A41: us-90283-2025-04-05-000000900019134 | B41: 90283 | C41: DEDUCTION | D41: CURRENT | E41: 4110 | F41: OR State Income Tax | I41: 5010.65 | K41: 408.24 | M41: 408.24 | N41: EMPLOYEE | O41: TAXABLE | P41: OTHER | Q41: US_TAX
A42: us-90283-2025-04-05-000000900019134 | B42: 90283 | C42: DEDUCTION | D42: CURRENT | E42: 4130 | F42: OR Statewide Transit Tax | I42: 5930.31 | K42: 5.93 | M42: 5.93 | N42: EMPLOYEE | O42: TAXABLE | P42: OTHER | Q42: US_TAX
A43: us-90283-2025-04-05-000000900019134 | B43: 90283 | C43: DEDUCTION | D43: CURRENT | E43: 5000 | F43: 401(k) Pre-Tax | K43: 842.31 | M43: 842.31 | N43: EMPLOYEE | O43: EXEMPT | P43: RETIREMENT | Q43: PRE_TAX_DEDUCTION
A44: us-90283-2025-04-05-000000900019134 | B44: 90283 | C44: DEDUCTION | D44: CURRENT | E44: 5120 | F44: Vision Pre-Tax | K44: 3.7 | M44: 3.7 | N44: EMPLOYEE | O44: EXEMPT | P44: HEALTH | Q44: PRE_TAX_DEDUCTION
A45: us-90283-2025-04-05-000000900019134 | B45: 90283 | C45: DEDUCTION | D45: CURRENT | E45: 5110 | F45: Dental Pre-Tax | K45: 9.9 | M45: 9.9 | N45: EMPLOYEE | O45: EXEMPT | P45: HEALTH | Q45: PRE_TAX_DEDUCTION
A46: us-90283-2025-04-05-000000900019134 | B46: 90283 | C46: DEDUCTION | D46: CURRENT | E46: 5100 | F46: Medical Pre-Tax | K46: 63.75 | M46: 63.75 | N46: EMPLOYEE | O46: EXEMPT | P46: HEALTH | Q46: PRE_TAX_DEDUCTION
A47: us-90283-2025-04-05-000000900019134 | B47: 90283 | C47: DEDUCTION | D47: CURRENT | E47: 6120 | F47: Domestic Partner Vision | K47: 2.96 | M47: 2.96 | N47: EMPLOYEE | O47: TAXABLE | P47: HEALTH | Q47: AFTER_TAX_DEDUCTION
A48: us-90283-2025-04-05-000000900019134 | B48: 90283 | C48: DEDUCTION | D48: CURRENT | E48: 6110 | F48: Domestic Partner Dental | K48: 9.9 | M48: 9.9 | N48: EMPLOYEE | O48: TAXABLE | P48: HEALTH | Q48: AFTER_TAX_DEDUCTION
A49: us-90283-2025-04-05-000000900019134 | B49: 90283 | C49: DEDUCTION | D49: CURRENT | E49: 6100 | F49: Domestic Partner Medical | K49: 86.06 | M49: 86.06 | N49: EMPLOYEE | O49: TAXABLE | P49: HEALTH | Q49: AFTER_TAX_DEDUCTION
A50: us-90283-2025-04-05-000000900019134 | B50: 90283 | C50: ER_CONTRIB | D50: CURRENT | E50: 7000 | F50: 401(k) Employer Match | L50: 168.46 | M50: 168.46 | N50: EMPLOYER | O50: EXEMPT | P50: RETIREMENT | Q50: EMPLOYER_PAID_BENEFIT
A51: us-90283-2025-04-05-000000900019134 | B51: 90283 | C51: ER_CONTRIB | D51: CURRENT | E51: 7100 | F51: Medical Employer Contribution | L51: 332.3 | M51: 332.3 | N51: EMPLOYER | O51: EXEMPT | P51: HEALTH | Q51: EMPLOYER_PAID_BENEFIT
A52: us-90372-2025-04-05-000000900028576 | B52: 90372 | C52: EARNING | D52: CURRENT | E52: 1000 | F52: Regular Salary | G52: HOURS | H52: 72 | J52: 34.86 | K52: 2509.58 | M52: 2509.58 | N52: EMPLOYEE | O52: TAXABLE | P52: OTHER | Q52: EARNING
A53: us-90372-2025-04-05-000000900028576 | B53: 90372 | C53: EARNING | D53: CURRENT | E53: 1110 | F53: Vacation Pay | G53: HOURS | H53: 8 | J53: 34.86 | K53: 278.88 | M53: 278.88 | N53: EMPLOYEE | O53: TAXABLE | P53: LEAVE | Q53: EARNING
A54: us-90372-2025-04-05-000000900028576 | B54: 90372 | C54: EARNING | D54: CURRENT | E54: 1510 | F54: Group Term Life Imputed | K54: 7.99 | M54: 7.99 | N54: EMPLOYEE | O54: TAXABLE | P54: OTHER | Q54: IMPUTED_INCOME
A55: us-90372-2025-04-05-000000900028576 | B55: 90372 | C55: DEDUCTION | D55: CURRENT | E55: 4010 | F55: Federal Income Tax | I55: 2425.98 | K55: 134.31 | M55: 134.31 | N55: EMPLOYEE | O55: TAXABLE | P55: OTHER | Q55: US_TAX
A56: us-90372-2025-04-05-000000900028576 | B56: 90372 | C56: DEDUCTION | D56: CURRENT | E56: 4050 | F56: Medicare EE | I56: 2565.4 | K56: 37.2 | M56: 37.2 | N56: EMPLOYEE | O56: TAXABLE | P56: HEALTH | Q56: US_TAX
A57: us-90372-2025-04-05-000000900028576 | B57: 90372 | C57: DEDUCTION | D57: CURRENT | E57: 4030 | F57: Social Security EE | I57: 2565.4 | K57: 159.05 | M57: 159.05 | N57: EMPLOYEE | O57: TAXABLE | P57: OTHER | Q57: US_TAX
A58: us-90372-2025-04-05-000000900028576 | B58: 90372 | C58: DEDUCTION | D58: CURRENT | E58: 4120 | F58: OR Paid Leave EE | I58: 2796.45 | K58: 16.78 | M58: 16.78 | N58: EMPLOYEE | O58: TAXABLE | P58: HEALTH | Q58: US_TAX
A59: us-90372-2025-04-05-000000900028576 | B59: 90372 | C59: DEDUCTION | D59: CURRENT | E59: 4110 | F59: OR State Income Tax | I59: 2425.98 | K59: 130.04 | M59: 130.04 | N59: EMPLOYEE | O59: TAXABLE | P59: OTHER | Q59: US_TAX
A60: us-90372-2025-04-05-000000900028576 | B60: 90372 | C60: DEDUCTION | D60: CURRENT | E60: 4130 | F60: OR Statewide Transit Tax | I60: 2796.45 | K60: 2.8 | M60: 2.8 | N60: EMPLOYEE | O60: TAXABLE | P60: OTHER | Q60: US_TAX
A61: us-90372-2025-04-05-000000900028576 | B61: 90372 | C61: DEDUCTION | D61: CURRENT | E61: 5000 | F61: 401(k) Pre-Tax | K61: 139.42 | M61: 139.42 | N61: EMPLOYEE | O61: EXEMPT | P61: RETIREMENT | Q61: PRE_TAX_DEDUCTION
A62: us-90372-2025-04-05-000000900028576 | B62: 90372 | C62: DEDUCTION | D62: CURRENT | E62: 5120 | F62: Vision Pre-Tax | K62: 12.05 | M62: 12.05 | N62: EMPLOYEE | O62: EXEMPT | P62: HEALTH | Q62: PRE_TAX_DEDUCTION
A63: us-90372-2025-04-05-000000900028576 | B63: 90372 | C63: DEDUCTION | D63: CURRENT | E63: 5110 | F63: Dental Pre-Tax | K63: 30.6 | M63: 30.6 | N63: EMPLOYEE | O63: EXEMPT | P63: HEALTH | Q63: PRE_TAX_DEDUCTION
A64: us-90372-2025-04-05-000000900028576 | B64: 90372 | C64: DEDUCTION | D64: CURRENT | E64: 5100 | F64: Medical Pre-Tax | K64: 188.4 | M64: 188.4 | N64: EMPLOYEE | O64: EXEMPT | P64: HEALTH | Q64: PRE_TAX_DEDUCTION
A65: us-90372-2025-04-05-000000900028576 | B65: 90372 | C65: ER_CONTRIB | D65: CURRENT | E65: 7000 | F65: 401(k) Employer Match | L65: 83.65 | M65: 83.65 | N65: EMPLOYER | O65: EXEMPT | P65: RETIREMENT | Q65: EMPLOYER_PAID_BENEFIT
A66: us-90372-2025-04-05-000000900028576 | B66: 90372 | C66: ER_CONTRIB | D66: CURRENT | E66: 7100 | F66: Medical Employer Contribution | L66: 1375.27 | M66: 1375.27 | N66: EMPLOYER | O66: EXEMPT | P66: HEALTH | Q66: EMPLOYER_PAID_BENEFIT
A67: us-90417-2025-06-14-000000900038344 | B67: 90417 | C67: EARNING | D67: CURRENT | E67: 1000 | F67: Regular Salary | G67: HOURS | H67: 80 | J67: 61.06 | K67: 4884.62 | M67: 4884.62 | N67: EMPLOYEE | O67: TAXABLE | P67: OTHER | Q67: EARNING
A68: us-90417-2025-06-14-000000900038344 | B68: 90417 | C68: EARNING | D68: CURRENT | E68: 1510 | F68: Group Term Life Imputed | K68: 3.76 | M68: 3.76 | N68: EMPLOYEE | O68: TAXABLE | P68: OTHER | Q68: IMPUTED_INCOME
A69: us-90417-2025-06-14-000000900038344 | B69: 90417 | C69: DEDUCTION | D69: CURRENT | E69: 4010 | F69: Federal Income Tax | I69: 4325.67 | K69: 629.11 | M69: 629.11 | N69: EMPLOYEE | O69: TAXABLE | P69: OTHER | Q69: US_TAX
A70: us-90417-2025-06-14-000000900038344 | B70: 90417 | C70: DEDUCTION | D70: CURRENT | E70: 4050 | F70: Medicare EE | I70: 4814.13 | K70: 69.8 | M70: 69.8 | N70: EMPLOYEE | O70: TAXABLE | P70: HEALTH | Q70: US_TAX
A71: us-90417-2025-06-14-000000900038344 | B71: 90417 | C71: DEDUCTION | D71: CURRENT | E71: 4030 | F71: Social Security EE | I71: 4814.13 | K71: 298.48 | M71: 298.48 | N71: EMPLOYEE | O71: TAXABLE | P71: OTHER | Q71: US_TAX
A72: us-90417-2025-06-14-000000900038344 | B72: 90417 | C72: DEDUCTION | D72: CURRENT | E72: 4120 | F72: OR Paid Leave EE | I72: 4888.38 | K72: 29.33 | M72: 29.33 | N72: EMPLOYEE | O72: TAXABLE | P72: HEALTH | Q72: US_TAX
A73: us-90417-2025-06-14-000000900038344 | B73: 90417 | C73: DEDUCTION | D73: CURRENT | E73: 4110 | F73: OR State Income Tax | I73: 4325.67 | K73: 337.38 | M73: 337.38 | N73: EMPLOYEE | O73: TAXABLE | P73: OTHER | Q73: US_TAX
A74: us-90417-2025-06-14-000000900038344 | B74: 90417 | C74: DEDUCTION | D74: CURRENT | E74: 4130 | F74: OR Statewide Transit Tax | I74: 4888.38 | K74: 4.89 | M74: 4.89 | N74: EMPLOYEE | O74: TAXABLE | P74: OTHER | Q74: US_TAX
A75: us-90417-2025-06-14-000000900038344 | B75: 90417 | C75: DEDUCTION | D75: CURRENT | E75: 5000 | F75: 401(k) Pre-Tax | K75: 488.46 | M75: 488.46 | N75: EMPLOYEE | O75: EXEMPT | P75: RETIREMENT | Q75: PRE_TAX_DEDUCTION
A76: us-90417-2025-06-14-000000900038344 | B76: 90417 | C76: DEDUCTION | D76: CURRENT | E76: 5120 | F76: Vision Pre-Tax | K76: 4.25 | M76: 4.25 | N76: EMPLOYEE | O76: EXEMPT | P76: HEALTH | Q76: PRE_TAX_DEDUCTION
A77: us-90417-2025-06-14-000000900038344 | B77: 90417 | C77: DEDUCTION | D77: CURRENT | E77: 5110 | F77: Dental Pre-Tax | K77: 10.2 | M77: 10.2 | N77: EMPLOYEE | O77: EXEMPT | P77: HEALTH | Q77: PRE_TAX_DEDUCTION
A78: us-90417-2025-06-14-000000900038344 | B78: 90417 | C78: DEDUCTION | D78: CURRENT | E78: 5100 | F78: Medical Pre-Tax | K78: 59.8 | M78: 59.8 | N78: EMPLOYEE | O78: EXEMPT | P78: HEALTH | Q78: PRE_TAX_DEDUCTION
A79: us-90417-2025-06-14-000000900038344 | B79: 90417 | C79: ER_CONTRIB | D79: CURRENT | E79: 7000 | F79: 401(k) Employer Match | L79: 146.54 | M79: 146.54 | N79: EMPLOYER | O79: EXEMPT | P79: RETIREMENT | Q79: EMPLOYER_PAID_BENEFIT
A80: us-90417-2025-06-14-000000900038344 | B80: 90417 | C80: ER_CONTRIB | D80: CURRENT | E80: 7100 | F80: Medical Employer Contribution | L80: 269.38 | M80: 269.38 | N80: EMPLOYER | O80: EXEMPT | P80: HEALTH | Q80: EMPLOYER_PAID_BENEFIT
A81: us-90487-2025-01-25-000000900046035 | B81: 90487 | C81: EARNING | D81: CURRENT | E81: 1000 | F81: Regular Salary | G81: HOURS | H81: 40 | J81: 51.92 | K81: 2077.05 | M81: 2077.05 | N81: EMPLOYEE | O81: TAXABLE | P81: OTHER | Q81: EARNING
A82: us-90487-2025-01-25-000000900046035 | B82: 90487 | C82: EARNING | D82: CURRENT | E82: 1110 | F82: Vacation Pay | G82: HOURS | H82: 40 | J82: 51.92 | K82: 2076.8 | M82: 2076.8 | N82: EMPLOYEE | O82: TAXABLE | P82: LEAVE | Q82: EARNING
A83: us-90487-2025-01-25-000000900046035 | B83: 90487 | C83: EARNING | D83: CURRENT | E83: 1510 | F83: Group Term Life Imputed | K83: 3.63 | M83: 3.63 | N83: EMPLOYEE | O83: TAXABLE | P83: OTHER | Q83: IMPUTED_INCOME
A84: us-90487-2025-01-25-000000900046035 | B84: 90487 | C84: DEDUCTION | D84: CURRENT | E84: 4010 | F84: Federal Income Tax | I84: 3451.37 | K84: 257.36 | M84: 257.36 | N84: EMPLOYEE | O84: TAXABLE | P84: OTHER | Q84: US_TAX
A85: us-90487-2025-01-25-000000900046035 | B85: 90487 | C85: DEDUCTION | D85: CURRENT | E85: 4050 | F85: Medicare EE | I85: 3949.83 | K85: 57.27 | M85: 57.27 | N85: EMPLOYEE | O85: TAXABLE | P85: HEALTH | Q85: US_TAX
A86: us-90487-2025-01-25-000000900046035 | B86: 90487 | C86: DEDUCTION | D86: CURRENT | E86: 4030 | F86: Social Security EE | I86: 3949.83 | K86: 244.89 | M86: 244.89 | N86: EMPLOYEE | O86: TAXABLE | P86: OTHER | Q86: US_TAX
A87: us-90487-2025-01-25-000000900046035 | B87: 90487 | C87: DEDUCTION | D87: CURRENT | E87: 4120 | F87: OR Paid Leave EE | I87: 4157.48 | K87: 24.94 | M87: 24.94 | N87: EMPLOYEE | O87: TAXABLE | P87: HEALTH | Q87: US_TAX
A88: us-90487-2025-01-25-000000900046035 | B88: 90487 | C88: DEDUCTION | D88: CURRENT | E88: 4110 | F88: OR State Income Tax | I88: 3451.37 | K88: 229.61 | M88: 229.61 | N88: EMPLOYEE | O88: TAXABLE | P88: OTHER | Q88: US_TAX
A89: us-90487-2025-01-25-000000900046035 | B89: 90487 | C89: DEDUCTION | D89: CURRENT | E89: 4130 | F89: OR Statewide Transit Tax | I89: 4157.48 | K89: 4.16 | M89: 4.16 | N89: EMPLOYEE | O89: TAXABLE | P89: OTHER | Q89: US_TAX
A90: us-90487-2025-01-25-000000900046035 | B90: 90487 | C90: DEDUCTION | D90: CURRENT | E90: 5000 | F90: 401(k) Pre-Tax | K90: 498.46 | M90: 498.46 | N90: EMPLOYEE | O90: EXEMPT | P90: RETIREMENT | Q90: PRE_TAX_DEDUCTION
A91: us-90487-2025-01-25-000000900046035 | B91: 90487 | C91: DEDUCTION | D91: CURRENT | E91: 5120 | F91: Vision Pre-Tax | K91: 10.9 | M91: 10.9 | N91: EMPLOYEE | O91: EXEMPT | P91: HEALTH | Q91: PRE_TAX_DEDUCTION
A92: us-90487-2025-01-25-000000900046035 | B92: 90487 | C92: DEDUCTION | D92: CURRENT | E92: 5110 | F92: Dental Pre-Tax | K92: 27.45 | M92: 27.45 | N92: EMPLOYEE | O92: EXEMPT | P92: HEALTH | Q92: PRE_TAX_DEDUCTION
A93: us-90487-2025-01-25-000000900046035 | B93: 90487 | C93: DEDUCTION | D93: CURRENT | E93: 5100 | F93: Medical Pre-Tax | K93: 169.3 | M93: 169.3 | N93: EMPLOYEE | O93: EXEMPT | P93: HEALTH | Q93: PRE_TAX_DEDUCTION
A94: us-90487-2025-01-25-000000900046035 | B94: 90487 | C94: ER_CONTRIB | D94: CURRENT | E94: 7000 | F94: 401(k) Employer Match | L94: 124.62 | M94: 124.62 | N94: EMPLOYER | O94: EXEMPT | P94: RETIREMENT | Q94: EMPLOYER_PAID_BENEFIT
A95: us-90487-2025-01-25-000000900046035 | B95: 90487 | C95: ER_CONTRIB | D95: CURRENT | E95: 7100 | F95: Medical Employer Contribution | L95: 1160.06 | M95: 1160.06 | N95: EMPLOYER | O95: EXEMPT | P95: HEALTH | Q95: EMPLOYER_PAID_BENEFIT
A96: us-90614-2025-07-12-000000900047520 | B96: 90614 | C96: EARNING | D96: CURRENT | E96: 1000 | F96: Regular Salary | G96: HOURS | H96: 72 | J96: 41.59 | K96: 2994.2 | M96: 2994.2 | N96: EMPLOYEE | O96: TAXABLE | P96: OTHER | Q96: EARNING
A97: us-90614-2025-07-12-000000900047520 | B97: 90614 | C97: EARNING | D97: CURRENT | E97: 1100 | F97: Holiday Pay | G97: HOURS | H97: 8 | J97: 41.59 | K97: 332.72 | M97: 332.72 | N97: EMPLOYEE | O97: TAXABLE | P97: LEAVE | Q97: EARNING
A98: us-90614-2025-07-12-000000900047520 | B98: 90614 | C98: EARNING | D98: CURRENT | E98: 1500 | F98: Domestic Partner Imputed Income | K98: 182.29 | M98: 182.29 | N98: EMPLOYEE | O98: TAXABLE | P98: OTHER | Q98: IMPUTED_INCOME
A99: us-90614-2025-07-12-000000900047520 | B99: 90614 | C99: EARNING | D99: CURRENT | E99: 1510 | F99: Group Term Life Imputed | K99: 7.06 | M99: 7.06 | N99: EMPLOYEE | O99: TAXABLE | P99: OTHER | Q99: IMPUTED_INCOME
A100: us-90614-2025-07-12-000000900047520 | B100: 90614 | C100: DEDUCTION | D100: CURRENT | E100: 4010 | F100: Federal Income Tax | I100: 3199.54 | K100: 381.36 | M100: 381.36 | N100: EMPLOYEE | O100: TAXABLE | P100: OTHER | Q100: US_TAX
...

Sheet Wage Type Catalog
A1: wage_type_local_lang | B1: wage_code | C1: no_of_occurrence | D1: total_pay | E1: average_pay | F1: category | G1: sub_category | H1: position | I1: employment_groups | J1: molga
A2: Regular Salary | B2: 1000 | C2: =COUNTIF('Pay Line Items'!$E$2:$E$165,B2) -> 10 | D2: =SUMIF('Pay Line Items'!$E$2:$E$165,B2,'Pay Line Items'!$M$2:$M$165) -> 29659.92 | E2: =IF(C2=0,0,D2/C2) -> 2965.992 | F2: Earning | G2: EARNING | H2: 1 | I2: BW1-Biweekly Salaried Exempt | J2: 10
A3: Holiday Pay | B3: 1100 | C3: =COUNTIF('Pay Line Items'!$E$2:$E$165,B3) -> 5 | D3: =SUMIF('Pay Line Items'!$E$2:$E$165,B3,'Pay Line Items'!$M$2:$M$165) -> 2100 | E3: =IF(C3=0,0,D3/C3) -> 420 | F3: Earning | G3: EARNING | H3: 2 | I3: BW1-Biweekly Salaried Exempt | J3: 10
A4: Vacation Pay | B4: 1110 | C4: =COUNTIF('Pay Line Items'!$E$2:$E$165,B4) -> 7 | D4: =SUMIF('Pay Line Items'!$E$2:$E$165,B4,'Pay Line Items'!$M$2:$M$165) -> 7586.24 | E4: =IF(C4=0,0,D4/C4) -> 1083.7486 | F4: Earning | G4: EARNING | H4: 3 | I4: BW1-Biweekly Salaried Exempt | J4: 10
A5: Domestic Partner Imputed Income | B5: 1500 | C5: =COUNTIF('Pay Line Items'!$E$2:$E$165,B5) -> 3 | D5: =SUMIF('Pay Line Items'!$E$2:$E$165,B5,'Pay Line Items'!$M$2:$M$165) -> 762.92 | E5: =IF(C5=0,0,D5/C5) -> 254.30667 | F5: Earning | G5: IMPUTED_INCOME | H5: 4 | I5: BW1-Biweekly Salaried Exempt | J5: 10
A6: Group Term Life Imputed | B6: 1510 | C6: =COUNTIF('Pay Line Items'!$E$2:$E$165,B6) -> 10 | D6: =SUMIF('Pay Line Items'!$E$2:$E$165,B6,'Pay Line Items'!$M$2:$M$165) -> 62.45 | E6: =IF(C6=0,0,D6/C6) -> 6.245 | F6: Earning | G6: IMPUTED_INCOME | H6: 5 | I6: BW1-Biweekly Salaried Exempt | J6: 10
A7: Federal Income Tax | B7: 4010 | C7: =COUNTIF('Pay Line Items'!$E$2:$E$165,B7) -> 10 | D7: =SUMIF('Pay Line Items'!$E$2:$E$165,B7,'Pay Line Items'!$M$2:$M$165) -> 3608.95 | E7: =IF(C7=0,0,D7/C7) -> 360.895 | F7: Deduction | G7: US_TAX | H7: 6 | I7: BW1-Biweekly Salaried Exempt | J7: 10
A8: Social Security EE | B8: 4030 | C8: =COUNTIF('Pay Line Items'!$E$2:$E$165,B8) -> 10 | D8: =SUMIF('Pay Line Items'!$E$2:$E$165,B8,'Pay Line Items'!$M$2:$M$165) -> 2397.18 | E8: =IF(C8=0,0,D8/C8) -> 239.718 | F8: Deduction | G8: US_TAX | H8: 7 | I8: BW1-Biweekly Salaried Exempt | J8: 10
A9: Medicare EE | B9: 4050 | C9: =COUNTIF('Pay Line Items'!$E$2:$E$165,B9) -> 10 | D9: =SUMIF('Pay Line Items'!$E$2:$E$165,B9,'Pay Line Items'!$M$2:$M$165) -> 560.64 | E9: =IF(C9=0,0,D9/C9) -> 56.064 | F9: Deduction | G9: US_TAX | H9: 8 | I9: BW1-Biweekly Salaried Exempt | J9: 10
A10: OR State Income Tax | B10: 4110 | C10: =COUNTIF('Pay Line Items'!$E$2:$E$165,B10) -> 10 | D10: =SUMIF('Pay Line Items'!$E$2:$E$165,B10,'Pay Line Items'!$M$2:$M$165) -> 2488.51 | E10: =IF(C10=0,0,D10/C10) -> 248.851 | F10: Deduction | G10: US_TAX | H10: 9 | I10: BW1-Biweekly Salaried Exempt | J10: 10
A11: OR Paid Leave EE | B11: 4120 | C11: =COUNTIF('Pay Line Items'!$E$2:$E$165,B11) -> 10 | D11: =SUMIF('Pay Line Items'!$E$2:$E$165,B11,'Pay Line Items'!$M$2:$M$165) -> 241.02 | E11: =IF(C11=0,0,D11/C11) -> 24.102 | F11: Deduction | G11: US_TAX | H11: 10 | I11: BW1-Biweekly Salaried Exempt | J11: 10
A12: OR Statewide Transit Tax | B12: 4130 | C12: =COUNTIF('Pay Line Items'!$E$2:$E$165,B12) -> 10 | D12: =SUMIF('Pay Line Items'!$E$2:$E$165,B12,'Pay Line Items'!$M$2:$M$165) -> 40.18 | E12: =IF(C12=0,0,D12/C12) -> 4.018 | F12: Deduction | G12: US_TAX | H12: 11 | I12: BW1-Biweekly Salaried Exempt | J12: 10
A13: 401(k) Pre-Tax | B13: 5000 | C13: =COUNTIF('Pay Line Items'!$E$2:$E$165,B13) -> 10 | D13: =SUMIF('Pay Line Items'!$E$2:$E$165,B13,'Pay Line Items'!$M$2:$M$165) -> 3975.58 | E13: =IF(C13=0,0,D13/C13) -> 397.558 | F13: Deduction | G13: PRE_TAX_DEDUCTION | H13: 12 | I13: BW1-Biweekly Salaried Exempt | J13: 10
... A21: Medical Employer Contribution | B21: 7100 | C21: =COUNTIF('Pay Line Items'!$E$2:$E$165,B21) -> 10 | D21: =SUMIF('Pay Line Items'!$E$2:$E$165,B21,'Pay Line Items'!$M$2:$M$165) -> 7724.64 | E21: =IF(C21=0,0,D21/C21) -> 772.464 | F21: Employer Contribution | G21: EMPLOYER_PAID_BENEFIT | H21: 20 | I21: BW1-Biweekly Salaried Exempt | J21: 10

Sheet Notes
A1: Notes
A2: All data is synthetic demo data regenerated from scratch; only the schema/format follows the source. No value, label or code is taken from the source payslip.
A3: Employer IDs use IRS-unassigned EIN prefixes; Oregon BINs start 00; bank accounts start 9999; streets and company names are invented. Collision with real records is unlikely but not guaranteed.
A4: Master Data: one row per employee, non-null scalar keys from the source JSON, renamed with underscores.
A5: Pay Line Items: every earning, deduction (tax, pre-tax, after-tax) and employer contribution line, joined to Master Data on payslip_id / employee_id.
A6: line_category is taken from the source line tags (US_TAX, PRE_TAX_DEDUCTION, AFTER_TAX_DEDUCTION, EMPLOYER_PAID_BENEFIT).
A7: Tax amounts are illustrative approximations (OASDI 6.2%, Medicare 1.45%, OR PFML 0.6%, OR transit 0.1%, simplified annualised federal/Oregon brackets). They are NOT statutory calculations; do not use to test tax logic.
A8: Amounts are stored as values, not formulas, so the sheets load cleanly into import tools.
A9: Wage Type Catalog: one row per unique wage code. wage_code values are demo codes (not SAP standard /4xx technical wage types). no_of_occurrence, total_pay and average_pay are live formulas over Pay Line Items. position = display sequence on the payslip. category = line section; sub_category = line category.
A10: Excluded: tags arrays, withholding (duplicates the tax lines), totals, ytd_totals, leave, counters, messages, source.
